Metadata-Version: 2.1
Name: ddx
Version: 0.1.0
Summary: 快速搭建基于Docker的Django项目
Home-page: https://github.com/ChanMo/ddx
Author: ChanMo
Author-email: chan.mo@outlook.com
License: UNKNOWN
Platform: UNKNOWN
